scanpy/__init__.py
scanpy/__main__.py
scanpy/_compat.py
scanpy/_settings.py
scanpy/_version.py
scanpy/cli.py
scanpy/logging.py
scanpy/readwrite.py
scanpy/_utils/__init__.py
scanpy/_utils/compute/is_constant.py
scanpy/datasets/10x_pbmc68k_reduced.h5ad
scanpy/datasets/__init__.py
scanpy/datasets/_datasets.py
scanpy/datasets/_ebi_expression_atlas.py
scanpy/datasets/_utils.py
scanpy/datasets/krumsiek11.txt
scanpy/datasets/toggleswitch.txt
scanpy/experimental/__init__.py
scanpy/experimental/_docs.py
scanpy/experimental/pp/__init__.py
scanpy/experimental/pp/_highly_variable_genes.py
scanpy/experimental/pp/_normalization.py
scanpy/experimental/pp/_recipes.py
scanpy/external/__init__.py
scanpy/external/exporting.py
scanpy/external/pl.py
scanpy/external/pp/__init__.py
scanpy/external/pp/_bbknn.py
scanpy/external/pp/_dca.py
scanpy/external/pp/_harmony_integrate.py
scanpy/external/pp/_hashsolo.py
scanpy/external/pp/_magic.py
scanpy/external/pp/_mnn_correct.py
scanpy/external/pp/_scanorama_integrate.py
scanpy/external/tl/__init__.py
scanpy/external/tl/_harmony_timeseries.py
scanpy/external/tl/_palantir.py
scanpy/external/tl/_phate.py
scanpy/external/tl/_phenograph.py
scanpy/external/tl/_pypairs.py
scanpy/external/tl/_sam.py
scanpy/external/tl/_trimap.py
scanpy/external/tl/_wishbone.py
scanpy/get/__init__.py
scanpy/get/_aggregated.py
scanpy/get/get.py
scanpy/metrics/__init__.py
scanpy/metrics/_common.py
scanpy/metrics/_gearys_c.py
scanpy/metrics/_metrics.py
scanpy/metrics/_morans_i.py
scanpy/neighbors/__init__.py
scanpy/neighbors/_common.py
scanpy/neighbors/_connectivity.py
scanpy/neighbors/_doc.py
scanpy/neighbors/_types.py
scanpy/neighbors/_backends/_common.py
scanpy/neighbors/_backends/rapids.py
scanpy/plotting/__init__.py
scanpy/plotting/_anndata.py
scanpy/plotting/_baseplot_class.py
scanpy/plotting/_docs.py
scanpy/plotting/_dotplot.py
scanpy/plotting/_matrixplot.py
scanpy/plotting/_preprocessing.py
scanpy/plotting/_qc.py
scanpy/plotting/_rcmod.py
scanpy-1.10.0.dist-info/METADATA
scanpy-1.10.0.dist-info/WHEEL
scanpy-1.10.0.dist-info/entry_points.txt
scanpy-1.10.0.dist-info/licenses/LICENSE
scanpy-1.10.0.dist-info/RECORD
