Metadata-Version: 2.3
Name: scanpy
Version: 1.10.0
Summary: Single-Cell Analysis in Python.
Project-URL: Documentation, https://scanpy.readthedocs.io/
Project-URL: Source, https://github.com/scverse/scanpy
Project-URL: Home-page, https://scanpy.org
Project-URL: Discourse, https://discourse.scverse.org/c/help/scanpy/37
Project-URL: Twitter, https://twitter.com/scverse_team
Author: Alex Wolf, Philipp Angerer, Fidel Ramirez, Isaac Virshup, Sergei Rybakov, Gokcen Eraslan, Tom White, Malte Luecken, Davide Cittaro, Tobias Callies, Marius Lange, Andrés R. Muñoz-Rojas
Maintainer-email: Isaac Virshup <ivirshup@gmail.com>, Philipp Angerer <phil.angerer@gmail.com>, Alex Wolf <f.alex.wolf@gmx.de>
License-Expression: BSD-3-Clause
License-File: LICENSE
Classifier: Development Status :: 5 - Production/Stable
Classifier: Environment :: Console
Classifier: Framework :: Jupyter
Classifier: Intended Audience :: Developers
Classifier: Intended Audience :: Science/Research
Classifier: License :: OSI Approved :: BSD License
Classifier: Natural Language :: English
Classifier: Operating System :: MacOS :: MacOS X
Classifier: Operating System :: Microsoft :: Windows
Classifier: Operating System :: POSIX :: Linux
Classifier: Programming Language :: Python :: 3
Classifier: Programming Language :: Python :: 3.9
Classifier: Programming Language :: Python :: 3.10
Classifier: Programming Language :: Python :: 3.11
Classifier: Programming Language :: Python :: 3.12
Classifier: Topic :: Scientific/Engineering :: Bio-Informatics
Classifier: Topic :: Scientific/Engineering :: Visualization
Requires-Python: >=3.9
Requires-Dist: anndata>=0.8
Requires-Dist: get-annotations; python_version < '3.10'
Requires-Dist: h5py>=3.1
Requires-Dist: joblib
Requires-Dist: legacy-api-wrap>=1.4
Requires-Dist: matplotlib>=3.6
Requires-Dist: natsort
Requires-Dist: networkx>=2.7
Requires-Dist: numba>=0.56
Requires-Dist: numpy>=1.23
Requires-Dist: packaging>=21.3
Requires-Dist: pandas>=1.5
Requires-Dist: patsy
Requires-Dist: pynndescent>=0.5
Requires-Dist: scikit-learn>=0.24
Requires-Dist: scipy>=1.8
Requires-Dist: seaborn>=0.13
Requires-Dist: session-info
Requires-Dist: statsmodels>=0.13
Requires-Dist: tqdm
Requires-Dist: umap-learn!=0.5.0,>=0.5
Provides-Extra: bbknn
Requires-Dist: bbknn; extra == 'bbknn'
Provides-Extra: dask
Requires-Dist: dask[array]>=2022.09.2; extra == 'dask'
Provides-Extra: dask-ml
Requires-Dist: dask-ml; extra == 'dask-ml'
Requires-Dist: scanpy[dask]; extra == 'dask-ml'
Provides-Extra: dev
Requires-Dist: pre-commit; extra == 'dev'
Requires-Dist: setuptools-scm; extra == 'dev'
Provides-Extra: doc
Requires-Dist: dask; extra == 'doc'
Requires-Dist: ipython>=7.20; extra == 'doc'
Requires-Dist: matplotlib!=3.6.1; extra == 'doc'
Requires-Dist: myst-nb>=1; extra == 'doc'
Requires-Dist: myst-parser>=2; extra == 'doc'
Requires-Dist: nbsphinx>=0.9; extra == 'doc'
Requires-Dist: readthedocs-sphinx-search; extra == 'doc'
Requires-Dist: sam-algorithm; extra == 'doc'
Requires-Dist: scanpy[paga]; extra == 'doc'
Requires-Dist: scanpydoc>=0.13.4; extra == 'doc'
Requires-Dist: setuptools; extra == 'doc'
Requires-Dist: sphinx-autodoc-typehints>=1.25.2; extra == 'doc'
Requires-Dist: sphinx-book-theme>=1.1.0; extra == 'doc'
Requires-Dist: sphinx-copybutton; extra == 'doc'
Requires-Dist: sphinx-design; extra == 'doc'
Requires-Dist: sphinx>=7; extra == 'doc'
Requires-Dist: sphinxcontrib-bibtex; extra == 'doc'
Requires-Dist: sphinxext-opengraph; extra == 'doc'
Provides-Extra: harmony
Requires-Dist: harmonypy; extra == 'harmony'
Provides-Extra: leiden
Requires-Dist: igraph>=0.10; extra == 'leiden'
Requires-Dist: leidenalg>=0.9.0; extra == 'leiden'
Provides-Extra: louvain
Requires-Dist: igraph; extra == 'louvain'
Requires-Dist: louvain!=0.6.2,>=0.6.0; extra == 'louvain'
Provides-Extra: magic
Requires-Dist: magic-impute>=2.0; extra == 'magic'
Provides-Extra: paga
Requires-Dist: igraph; extra == 'paga'
Provides-Extra: rapids
Requires-Dist: cudf>=0.9; extra == 'rapids'
Requires-Dist: cugraph>=0.9; extra == 'rapids'
Requires-Dist: cuml>=0.9; extra == 'rapids'
Provides-Extra: scanorama
Requires-Dist: scanorama; extra == 'scanorama'
Provides-Extra: scrublet
Requires-Dist: scikit-image; extra == 'scrublet'
Provides-Extra: skmisc
Requires-Dist: scikit-misc>=0.1.3; extra == 'skmisc'
Provides-Extra: test
Requires-Dist: scanpy[dask]; extra == 'test'
Requires-Dist: scanpy[leiden]; extra == 'test'
Requires-Dist: scanpy[scrublet]; extra == 'test'
Requires-Dist: scanpy[test-min]; extra == 'test'
Requires-Dist: zarr; extra == 'test'
Provides-Extra: test-full
Requires-Dist: scanpy[dask-ml]; extra == 'test-full'
Requires-Dist: scanpy[harmony]; extra == 'test-full'
Requires-Dist: scanpy[louvain]; extra == 'test-full'
Requires-Dist: scanpy[magic]; extra == 'test-full'
Requires-Dist: scanpy[scanorama]; extra == 'test-full'
Requires-Dist: scanpy[skmisc]; extra == 'test-full'
Requires-Dist: scanpy[test]; extra == 'test-full'
Provides-Extra: test-min
Requires-Dist: profimp; extra == 'test-min'
Requires-Dist: pytest-cov; extra == 'test-min'
Requires-Dist: pytest-mock; extra == 'test-min'
Requires-Dist: pytest-nunit; extra == 'test-min'
Requires-Dist: pytest>=7.4.2; extra == 'test-min'
